latex_generator_lib/__init__.py
latex_generator_lib/img_gen.py
latex_generator_lib/table_gen.py
latex_generator_lib-0.1.3.dist-info/METADATA
latex_generator_lib-0.1.3.dist-info/WHEEL
latex_generator_lib-0.1.3.dist-info/RECORD
