Metadata-Version: 2.3
Name: latex_generator_lib
Version: 0.1.3
Summary: Package for generating LaTeX code
Author: ilia-anikeev
Author-email: ilia.anikeev@gmail.com
Requires-Python: >=3.12
Classifier: Programming Language :: Python :: 3
Classifier: Programming Language :: Python :: 3.12
Classifier: Programming Language :: Python :: 3.13
